data_designer/cli/README.md
data_designer/cli/__init__.py
data_designer/cli/main.py
data_designer/cli/ui.py
data_designer/cli/utils.py
data_designer/cli/commands/__init__.py
data_designer/cli/commands/download.py
data_designer/cli/commands/list.py
data_designer/cli/commands/models.py
data_designer/cli/commands/providers.py
data_designer/cli/commands/reset.py
data_designer/cli/controllers/__init__.py
data_designer/cli/controllers/download_controller.py
data_designer/cli/controllers/model_controller.py
data_designer/cli/controllers/provider_controller.py
data_designer/cli/forms/__init__.py
data_designer/cli/forms/builder.py
data_designer/cli/forms/field.py
data_designer/cli/forms/form.py
data_designer/cli/forms/model_builder.py
data_designer/cli/forms/provider_builder.py
data_designer/cli/repositories/__init__.py
data_designer/cli/repositories/base.py
data_designer/cli/repositories/model_repository.py
data_designer/cli/repositories/persona_repository.py
data_designer/cli/repositories/provider_repository.py
data_designer/cli/services/__init__.py
data_designer/cli/services/download_service.py
data_designer/cli/services/model_service.py
data_designer/cli/services/provider_service.py
data_designer/interface/__init__.py
data_designer/interface/_version.py
data_designer/interface/data_designer.py
data_designer/interface/errors.py
data_designer/interface/results.py
data_designer-0.4.0.dist-info/METADATA
data_designer-0.4.0.dist-info/WHEEL
data_designer-0.4.0.dist-info/entry_points.txt
data_designer-0.4.0.dist-info/RECORD
