Metadata-Version: 2.4
Name: data-designer
Version: 0.4.0
Summary: General framework for synthetic data generation
License-Expression: Apache-2.0
Classifier: Development Status :: 4 - Beta
Classifier: Intended Audience :: Developers
Classifier: Intended Audience :: Science/Research
Classifier: License :: OSI Approved :: Apache Software License
Classifier: Programming Language :: Python :: 3.10
Classifier: Programming Language :: Python :: 3.11
Classifier: Programming Language :: Python :: 3.12
Classifier: Programming Language :: Python :: 3.13
Classifier: Topic :: Scientific/Engineering :: Artificial Intelligence
Classifier: Topic :: Software Development
Requires-Python: >=3.10
Requires-Dist: data-designer-config
Requires-Dist: data-designer-engine
Requires-Dist: prompt-toolkit<4,>=3.0.0
Requires-Dist: typer<1,>=0.12.0
